dgtl_logging/__init__.py
dgtl_logging/dgtl_logging.py
dgtl_logging/integration_test.py
dgtl_logging/integration_test_sub.py
dgtl_logging/unit_test.py
dgtl_logging-0.2.0.dist-info/METADATA
dgtl_logging-0.2.0.dist-info/WHEEL
dgtl_logging-0.2.0.dist-info/top_level.txt
dgtl_logging-0.2.0.dist-info/RECORD
