Metadata-Version: 2.1
Name: dgtl_logging
Version: 0.2.0
Summary: DGTL Health BV NEN7513 compliant logging objects 
Author: Olivier Witteman
License: MIT
Requires-Dist: uuid
